autowinpy/__init__.py
autowinpy/atk/__init__.py
autowinpy/atk/_combobox.py
autowinpy/atk/_function.py
autowinpy/core/__init__.py
autowinpy/core/_cls_gui.py
autowinpy/core/_cls_template.py
autowinpy/core/_system.py
autowinpy/type/__init__.py
autowinpy/type/_image.py
autowinpy/type/_rect.py
autowinpy/win32/__init__.py
autowinpy/win32/_handle.py
autowinpy-0.4.1.dist-info/LICENSE
autowinpy-0.4.1.dist-info/METADATA
autowinpy-0.4.1.dist-info/WHEEL
autowinpy-0.4.1.dist-info/top_level.txt
autowinpy-0.4.1.dist-info/RECORD
