Metadata-Version: 2.1
Name: autowinpy
Version: 0.4.1
Summary: Foreground automation support for Windows OS
Home-page: https://github.com/soma0sd/autowinpy
Author: soma0sd
Author-email: soma0sd@gmail.com
License: MIT
Download-URL: https://github.com/soma0sd/autowinpy/archive/0.4.1.tar.gz
Project-URL: AutoWinPy documentation, https://soma0sd.github.io/autowinpy/
Project-URL: AutoWinPy source, https://github.com/soma0sd/autowinpy
Keywords: windows,automation,macro
Platform: UNKNOWN
Classifier: Natural Language :: Korean
Classifier: Operating System :: Microsoft :: Windows
Classifier: License :: OSI Approved :: MIT License
Classifier: Programming Language :: Python :: 3
Classifier: Programming Language :: Python :: 3 :: Only
Classifier: Programming Language :: Python :: 3.4
Classifier: Programming Language :: Python :: 3.5
Classifier: Programming Language :: Python :: 3.6
Classifier: Programming Language :: Python :: 3.7
Classifier: Programming Language :: Python :: 3.8
Requires-Python: >=3.4
Requires-Dist: pywin32
Requires-Dist: opencv-python
Requires-Dist: numpy
Requires-Dist: Pillow
